Metadata-Version: 2.1
Name: smart-match
Version: 0.1.1
Summary: A smart match package
Home-page: https://github.com/jiayingwang/smart_match
Author: Jiaying Wang
Author-email: jiaying@sjzu.edu.cn
License: UNKNOWN
Platform: UNKNOWN
Classifier: Programming Language :: Python :: 3
Classifier: License :: OSI Approved :: MIT License
Classifier: Operating System :: OS Independent
Requires-Python: >=3.6
